tsd2gspread/__init__.py
tsd2gspread/py.typed
tsd2gspread-0.3.0.dist-info/METADATA
tsd2gspread-0.3.0.dist-info/WHEEL
tsd2gspread-0.3.0.dist-info/licenses/LICENSE
tsd2gspread-0.3.0.dist-info/RECORD
