Metadata-Version: 2.4
Name: tsd2gspread
Version: 0.3.0
Summary: Time Series Data to Google Sheets
Project-URL: Repository, https://github.com/rcmdnk/tsd2gspread
Project-URL: Homepage, https://github.com/rcmdnk/tsd2gspread
Author-email: rcmdnk <rcmdnk@gmail.com>
License-Expression: Apache-2.0
License-File: LICENSE
Keywords: API,Data,Google,Sheets,Spreadsheets
Requires-Python: >=3.9
Requires-Dist: gspread>=6.1.2
